keeper/__init__.py
keeper/keeper.py
keeper/refcount.py
keeper/streams.py
keeper/values.py
keeper/version.py
keeper/storage/__init__.py
keeper/storage/filestorage.py
keeper/storage/storage.py
keeper/storage/streams.py
keeper/storage/writecachestorage.py
keeper-1.1.1.dist-info/LICENSE.txt
keeper-1.1.1.dist-info/METADATA
keeper-1.1.1.dist-info/WHEEL
keeper-1.1.1.dist-info/top_level.txt
keeper-1.1.1.dist-info/RECORD
