Metadata-Version: 2.1
Name: keeper
Version: 1.1.1
Summary: A file-based value store for bytes and strings.
Home-page: https://github.com/rob-smallshire/keeper/
Author: Robert Smallshire
Author-email: robert@smallshire.org.uk
License: MIT License
Download-URL: https://github.com/rob-smallshire/keeper/archive/master.zip
Keywords: Python
Platform: UNKNOWN
Classifier: Development Status :: 3 - Alpha
Classifier: Programming Language :: Python
Classifier: Programming Language :: Python :: 3
Classifier: Environment :: Other Environment
Classifier: Intended Audience :: Developers
Classifier: License :: OSI Approved :: MIT License
Classifier: Operating System :: OS Independent
Classifier: Topic :: Software Development :: Libraries :: Python Modules
Classifier: Topic :: Utilities
Requires-Dist: atomicwrites
